gctf/__init__.py
gctf/bibtex.py
gctf/constants.py
gctf/protocols.conf
gctf/viewers.py
gctf/wizards.py
gctf/convert/__init__.py
gctf/convert/convert.py
gctf/convert/dataimport.py
gctf/protocols/__init__.py
gctf/protocols/program_gctf.py
gctf/protocols/protocol_gctf.py
gctf/protocols/protocol_ts_gctf.py
gctf/tests/__init__.py
gctf/tests/test_protocols_gctf.py
gctf/tests/test_protocols_gctf_ts.py
scipion_em_gctf-3.2.2.dist-info/LICENSE
scipion_em_gctf-3.2.2.dist-info/METADATA
scipion_em_gctf-3.2.2.dist-info/WHEEL
scipion_em_gctf-3.2.2.dist-info/entry_points.txt
scipion_em_gctf-3.2.2.dist-info/top_level.txt
scipion_em_gctf-3.2.2.dist-info/RECORD
